wdq/app/__init__.py
wdq/app/main.py
wdq/app/core/__init__.py
wdq/app/core/config.py
wdq/app/core/exceptions.py
wdq/app/core/logging.py
wdq/app/core/security.py
wdq/app/db/__init__.py
wdq/app/db/database.py
wdq/app/dependencies/__init__.py
wdq/app/dependencies/auth.py
wdq/app/dependencies/db_session.py
wdq/app/middleware/__init__.py
wdq/app/middleware/request_id.py
wdq/app/models/__init__.py
wdq/app/models/base.py
wdq/app/models/item.py
wdq/app/models/user.py
wdq/app/routers/__init__.py
wdq/app/routers/admin/dashboard.py
wdq/app/routers/v1/items.py
wdq/app/routers/v1/users.py
wdq/app/schemas/__init__.py
wdq/app/schemas/item.py
wdq/app/schemas/user.py
wdq/app/services/__init__.py
wdq/app/services/item_service.py
wdq/app/services/user_service.py
wdq/tests/__init__.py
wdq/tests/conftest.py
wdq/tests/test_items.py
wdq/tests/test_users.py
fastapi_cookiecutters-0.2.1.dist-info/METADATA
fastapi_cookiecutters-0.2.1.dist-info/WHEEL
fastapi_cookiecutters-0.2.1.dist-info/top_level.txt
fastapi_cookiecutters-0.2.1.dist-info/RECORD
