Metadata-Version: 2.2
Name: fastapi-cookiecutters
Version: 0.2.1
Summary: A customizable Cookiecutter template for generating production-ready FastAPI projects
Author-email: Mohammad <mohammades13851@gmail.com>
Project-URL: Homepage, https://github.com/Mohammad222PR/fastapi-cookiecutter
Project-URL: Documentation, https://github.com/Mohammad222PR/fastapi-cookiecutter/blob/main/README.md
Project-URL: Issues, https://github.com/Mohammad222PR/fastapi-cookiecutter/issues
Keywords: fastapi,cookiecutter,template,api,web-development,python
Classifier: Programming Language :: Python :: 3
Classifier: Programming Language :: Python :: 3.11
Classifier: License :: OSI Approved :: MIT License
Classifier: Operating System :: OS Independent
Classifier: Development Status :: 4 - Beta
Classifier: Intended Audience :: Developers
Classifier: Topic :: Software Development :: Libraries :: Python Modules
Classifier: Topic :: Internet :: WWW/HTTP
Classifier: Topic :: Utilities
Requires-Python: >=3.11
Requires-Dist: cookiecutter>=2.6.0
